[{"year_sem": "1101", "course_id": "070078001"}, {"year_sem": "1091", "course_id": "070078001"}, {"year_sem": "1091", "course_id": "070221001"}, {"year_sem": "1082", "course_id": "070078001"}, {"year_sem": "1082", "course_id": "070198001"}, {"year_sem": "1101", "course_id": "070078001"}, {"year_sem": "1091", "course_id": "070078001"}, {"year_sem": "1091", "course_id": "070221001"}, {"year_sem": "1082", "course_id": "070078001"}, {"year_sem": "1082", "course_id": "070198001"}, {"year_sem": "1101", "course_id": "070078001"}, {"year_sem": "1091", "course_id": "070078001"}, {"year_sem": "1091", "course_id": "070221001"}, {"year_sem": "1082", "course_id": "070078001"}, {"year_sem": "1082", "course_id": "070198001"}]