[{"year_sem": "1092", "course_id": "032002011"}, {"year_sem": "1092", "course_id": "032002221"}, {"year_sem": "1092", "course_id": "032002611"}, {"year_sem": "1092", "course_id": "032002901"}, {"year_sem": "1082", "course_id": "032002021"}, {"year_sem": "1082", "course_id": "032002411"}, {"year_sem": "1082", "course_id": "032002711"}, {"year_sem": "1082", "course_id": "032002911"}, {"year_sem": "1072", "course_id": "032002011"}, {"year_sem": "1072", "course_id": "032002421"}, {"year_sem": "1072", "course_id": "032002621"}, {"year_sem": "1072", "course_id": "032002911"}, {"year_sem": "1102", "course_id": "032002031"}, {"year_sem": "1102", "course_id": "032002421"}, {"year_sem": "1102", "course_id": "032002611"}, {"year_sem": "1092", "course_id": "032002011"}, {"year_sem": "1092", "course_id": "032002221"}, {"year_sem": "1092", "course_id": "032002611"}, {"year_sem": "1092", "course_id": "032002901"}, {"year_sem": "1082", "course_id": "032002021"}, {"year_sem": "1082", "course_id": "032002411"}, {"year_sem": "1082", "course_id": "032002711"}, {"year_sem": "1082", "course_id": "032002911"}, {"year_sem": "1102", "course_id": "032002031"}, {"year_sem": "1102", "course_id": "032002421"}, {"year_sem": "1102", "course_id": "032002611"}, {"year_sem": "1092", "course_id": "032002011"}, {"year_sem": "1092", "course_id": "032002221"}, {"year_sem": "1092", "course_id": "032002611"}, {"year_sem": "1092", "course_id": "032002901"}, {"year_sem": "1082", "course_id": "032002021"}, {"year_sem": "1082", "course_id": "032002411"}, {"year_sem": "1082", "course_id": "032002711"}, {"year_sem": "1082", "course_id": "032002911"}, {"year_sem": "1102", "course_id": "032002031"}, {"year_sem": "1102", "course_id": "032002421"}, {"year_sem": "1102", "course_id": "032002611"}, {"year_sem": "1092", "course_id": "032002011"}, {"year_sem": "1092", "course_id": "032002221"}, {"year_sem": "1092", "course_id": "032002611"}, {"year_sem": "1092", "course_id": "032002901"}, {"year_sem": "1082", "course_id": "032002021"}, {"year_sem": "1082", "course_id": "032002411"}, {"year_sem": "1082", "course_id": "032002711"}, {"year_sem": "1082", "course_id": "032002911"}]